gom/__init__.py
gom/api.py
gom/config.py
gom/nlp.py
gom/types.py
gom/cli/__init__.py
gom/cli/preprocess.py
gom/cli/vqa.py
gom/detectors/__init__.py
gom/detectors/base.py
gom/detectors/detectron2.py
gom/detectors/grounding_dino.py
gom/detectors/manager.py
gom/detectors/owlvit.py
gom/detectors/yolov8.py
gom/fusion/__init__.py
gom/fusion/benchmark.py
gom/fusion/cascade.py
gom/fusion/confluence.py
gom/fusion/nms.py
gom/fusion/spatial_hash.py
gom/fusion/wbf.py
gom/fusion/wbf_optimized.py
gom/graph/prompt.py
gom/graph/scene_graph.py
gom/graph/utils.py
gom/pipeline/preprocessor.py
gom/relations/clip_rel.py
gom/relations/inference.py
gom/relations/llm_guided.py
gom/relations/physics.py
gom/relations/semantic_filter.py
gom/relations/spatial_3d.py
gom/relations/geometry/__init__.py
gom/relations/geometry/core.py
gom/relations/geometry/masks.py
gom/relations/geometry/nearest.py
gom/relations/geometry/predicates.py
gom/relations/geometry/vectorized.py
gom/segmentation/__init__.py
gom/segmentation/base.py
gom/segmentation/fastsam.py
gom/segmentation/refinement.py
gom/segmentation/sam1.py
gom/segmentation/sam2.py
gom/segmentation/samhq.py
gom/utils/batch_processing.py
gom/utils/boxes.py
gom/utils/cache.py
gom/utils/cache_advanced.py
gom/utils/calibration.py
gom/utils/clip_cache.py
gom/utils/clip_utils.py
gom/utils/colors.py
gom/utils/depth.py
gom/utils/depth_v2.py
gom/utils/detector_utils.py
gom/utils/ensemble.py
gom/utils/gpu_memory.py
gom/utils/mixed_precision.py
gom/utils/model_registry.py
gom/utils/tta.py
gom/viz/rendering_opt.py
gom/viz/visualizer.py
gom/vqa/io.py
gom/vqa/models.py
gom/vqa/preproc.py
gom/vqa/runner.py
gom/vqa/types.py
graph_of_mark-1.1.0.dist-info/licenses/LICENSE
graph_of_mark-1.1.0.dist-info/METADATA
graph_of_mark-1.1.0.dist-info/WHEEL
graph_of_mark-1.1.0.dist-info/entry_points.txt
graph_of_mark-1.1.0.dist-info/top_level.txt
graph_of_mark-1.1.0.dist-info/RECORD
