Metadata-Version: 2.4
Name: graph-of-mark
Version: 1.1.0
Summary: Visual scene understanding pipeline with multi-model detection, segmentation, and scene graph generation
Home-page: https://github.com/disi-unibo-nlp/graph-of-mark
Author: DISI-UNIBO-NLP
Author-email: 
License-Expression: MIT
Project-URL: Homepage, https://github.com/disi-unibo-nlp/graph-of-mark
Project-URL: Documentation, https://github.com/disi-unibo-nlp/graph-of-mark#readme
Project-URL: Repository, https://github.com/disi-unibo-nlp/graph-of-mark
Project-URL: Bug Reports, https://github.com/disi-unibo-nlp/graph-of-mark/issues
Keywords: computer-vision,scene-graph,object-detection,segmentation,visual-question-answering,sam,yolo,clip,deep-learning,pytorch
Classifier: Development Status :: 4 - Beta
Classifier: Intended Audience :: Developers
Classifier: Intended Audience :: Science/Research
Classifier: Topic :: Scientific/Engineering :: Artificial Intelligence
Classifier: Topic :: Scientific/Engineering :: Image Recognition
Classifier: Programming Language :: Python :: 3
Classifier: Programming Language :: Python :: 3.8
Classifier: Programming Language :: Python :: 3.9
Classifier: Programming Language :: Python :: 3.10
Classifier: Programming Language :: Python :: 3.11
Classifier: Programming Language :: Python :: 3.12
Classifier: Operating System :: POSIX :: Linux
Classifier: Operating System :: MacOS :: MacOS X
Classifier: Environment :: GPU :: NVIDIA CUDA
Requires-Python: >=3.8
License-File: LICENSE
Requires-Dist: torch>=2.0.0
Requires-Dist: torchvision>=0.15.0
Requires-Dist: pillow>=9.0.0
Requires-Dist: numpy>=1.24.0
Requires-Dist: opencv-python>=4.8.0
Requires-Dist: transformers>=4.36.0
Requires-Dist: networkx>=3.1
Requires-Dist: matplotlib>=3.5.0
Requires-Dist: tqdm>=4.65.0
Requires-Dist: datasets>=2.14.0
Requires-Dist: sentence-transformers>=2.2.0
Requires-Dist: ensemble-boxes>=1.0.7
Requires-Dist: huggingface_hub>=0.16.0
Requires-Dist: psutil>=5.9.5
Requires-Dist: omegaconf
Requires-Dist: pycocotools
Requires-Dist: scipy>=1.11.4
Requires-Dist: pyyaml
Requires-Dist: fvcore>=0.1.5
Requires-Dist: iopath>=0.1.7
Requires-Dist: hydra-core>=1.3.2
Requires-Dist: einops
Requires-Dist: timm>=0.9.0
Requires-Dist: spacy>=3.5.0
Requires-Dist: nltk>=3.8.0
Requires-Dist: blis>=0.7.11
Requires-Dist: colorlog>=6.0.0
Requires-Dist: pretty-errors>=1.2.25
Requires-Dist: sentencepiece>=0.1.99
Requires-Dist: num2words>=0.5.10
Provides-Extra: segmentation
Requires-Dist: segment-anything-hq; extra == "segmentation"
Provides-Extra: sam2
Provides-Extra: detection
Requires-Dist: ultralytics>=8.0.0; extra == "detection"
Provides-Extra: depth
Requires-Dist: depth-anything-v2; extra == "depth"
Provides-Extra: vqa
Requires-Dist: accelerate>=0.20.0; extra == "vqa"
Requires-Dist: peft>=0.5.0; extra == "vqa"
Provides-Extra: dev
Requires-Dist: pytest>=7.0.0; extra == "dev"
Requires-Dist: pytest-cov>=4.0.0; extra == "dev"
Requires-Dist: black>=23.0.0; extra == "dev"
Requires-Dist: isort>=5.12.0; extra == "dev"
Requires-Dist: mypy>=1.0.0; extra == "dev"
Requires-Dist: flake8>=6.0.0; extra == "dev"
Requires-Dist: jupyter>=1.0.0; extra == "dev"
Requires-Dist: ipykernel>=6.20.0; extra == "dev"
Provides-Extra: visualization
Requires-Dist: adjustText>=0.7.3; extra == "visualization"
Provides-Extra: logging
Requires-Dist: wandb>=0.15.0; extra == "logging"
Provides-Extra: all
Requires-Dist: segment-anything-hq; extra == "all"
Requires-Dist: ultralytics>=8.0.0; extra == "all"
Requires-Dist: depth-anything-v2; extra == "all"
Requires-Dist: accelerate>=0.20.0; extra == "all"
Requires-Dist: peft>=0.5.0; extra == "all"
Requires-Dist: adjustText>=0.7.3; extra == "all"
Requires-Dist: wandb>=0.15.0; extra == "all"
Provides-Extra: all-mps
Requires-Dist: segment-anything-hq; extra == "all-mps"
Requires-Dist: ultralytics>=8.0.0; extra == "all-mps"
Requires-Dist: depth-anything-v2; extra == "all-mps"
Requires-Dist: accelerate>=0.20.0; extra == "all-mps"
Requires-Dist: qwen-vl-utils>=0.0.10; extra == "all-mps"
Requires-Dist: peft>=0.5.0; extra == "all-mps"
Requires-Dist: adjustText>=0.7.3; extra == "all-mps"
Requires-Dist: wandb>=0.15.0; extra == "all-mps"
Dynamic: home-page
Dynamic: license-file
Dynamic: requires-python
